few_shot/__init__.py
few_shot/decorator.py
few_shot/example.py
few_shot/exceptions.py
few_shot/formatter.py
few_shot-0.3.0.dist-info/LICENSE
few_shot-0.3.0.dist-info/METADATA
few_shot-0.3.0.dist-info/WHEEL
few_shot-0.3.0.dist-info/RECORD
